clitools/__init__.py
clitools/cli.py
clitools/command.py
clitools/command_group.py
clitools/command_group_master.py
clitools/config/__init__.py
clitools/config/common.py
clitools/config/config_files_initiatior.py
clitools/config/config_loader.py
clitools/config/yaml_parser.py
clitools/core.py
clitools/foo.py
clitools/screens/pick_command.py
clitools/screens/pick_group.py
keeps-0.0.1.dist-info/entry_points.txt
keeps-0.0.1.dist-info/LICENSE
keeps-0.0.1.dist-info/WHEEL
keeps-0.0.1.dist-info/METADATA
keeps-0.0.1.dist-info/RECORD
