Metadata-Version: 2.1
Name: keeps
Version: 0.0.1
Summary: Test project
Home-page: https://github.com/fpgmaas/clitools
Author: Florian Maas
Author-email: ffpgmaas@gmail.com
Requires-Python: >=3.8,<=3.11
Classifier: Programming Language :: Python :: 3
Classifier: Programming Language :: Python :: 3.8
Classifier: Programming Language :: Python :: 3.9
Classifier: Programming Language :: Python :: 3.10
Classifier: Programming Language :: Python :: 3.11
Requires-Dist: click (>=8.1.3,<9.0.0)
Requires-Dist: keyboard (>=0.13.5,<0.14.0)
Requires-Dist: pyyaml (>=6.0,<7.0)
Project-URL: Documentation, https://fpgmaas.github.io/clitools/
Project-URL: Repository, https://github.com/fpgmaas/clitools
